py4DSTEM/__init__.py
py4DSTEM/version.py
py4DSTEM/braggvectors/__init__.py
py4DSTEM/braggvectors/braggvector_methods.py
py4DSTEM/braggvectors/braggvectors.py
py4DSTEM/braggvectors/diskdetection.py
py4DSTEM/braggvectors/diskdetection_aiml.py
py4DSTEM/braggvectors/diskdetection_aiml_cuda.py
py4DSTEM/braggvectors/diskdetection_cuda.py
py4DSTEM/braggvectors/diskdetection_parallel.py
py4DSTEM/braggvectors/diskdetection_parallel_new.py
py4DSTEM/braggvectors/kernels.py
py4DSTEM/braggvectors/multicorr_col_kernel.cu
py4DSTEM/braggvectors/multicorr_row_kernel.cu
py4DSTEM/braggvectors/probe.py
py4DSTEM/braggvectors/threshold.py
py4DSTEM/data/__init__.py
py4DSTEM/data/calibration.py
py4DSTEM/data/data.py
py4DSTEM/data/diffractionslice.py
py4DSTEM/data/propagating_calibration.py
py4DSTEM/data/qpoints.py
py4DSTEM/data/realslice.py
py4DSTEM/datacube/__init__.py
py4DSTEM/datacube/datacube.py
py4DSTEM/datacube/virtualdiffraction.py
py4DSTEM/datacube/virtualimage.py
py4DSTEM/io/__init__.py
py4DSTEM/io/google_drive_downloader.py
py4DSTEM/io/importfile.py
py4DSTEM/io/parsefiletype.py
py4DSTEM/io/read.py
py4DSTEM/io/save.py
py4DSTEM/io/filereaders/__init__.py
py4DSTEM/io/filereaders/empad.py
py4DSTEM/io/filereaders/read_K2.py
py4DSTEM/io/filereaders/read_abTEM.py
py4DSTEM/io/filereaders/read_arina.py
py4DSTEM/io/filereaders/read_dm.py
py4DSTEM/io/filereaders/read_mib.py
py4DSTEM/io/legacy/__init__.py
py4DSTEM/io/legacy/read_legacy_12.py
py4DSTEM/io/legacy/read_legacy_13.py
py4DSTEM/io/legacy/read_utils.py
py4DSTEM/io/legacy/legacy12/__init__.py
py4DSTEM/io/legacy/legacy12/read_utils_v0_12.py
py4DSTEM/io/legacy/legacy12/read_utils_v0_5.py
py4DSTEM/io/legacy/legacy12/read_utils_v0_6.py
py4DSTEM/io/legacy/legacy12/read_utils_v0_7.py
py4DSTEM/io/legacy/legacy12/read_utils_v0_9.py
py4DSTEM/io/legacy/legacy12/read_v0_12.py
py4DSTEM/io/legacy/legacy12/read_v0_5.py
py4DSTEM/io/legacy/legacy12/read_v0_6.py
py4DSTEM/io/legacy/legacy12/read_v0_7.py
py4DSTEM/io/legacy/legacy12/read_v0_9.py
py4DSTEM-0.14.18.dist-info/METADATA
py4DSTEM-0.14.18.dist-info/WHEEL
py4DSTEM-0.14.18.dist-info/top_level.txt
py4DSTEM-0.14.18.dist-info/RECORD
