Metadata-Version: 2.2
Name: py4DSTEM
Version: 0.14.18
Summary: An open source python package for processing and analysis of 4D STEM data.
Home-page: https://github.com/py4dstem/py4DSTEM/
Author: Benjamin H. Savitzky
Author-email: ben.savitzky@gmail.com
License: GNU GPLv3
Keywords: STEM,4DSTEM
Requires-Python: >=3.10
Requires-Dist: numpy<2.0,>=1.19
Requires-Dist: scipy>=1.5.2
Requires-Dist: h5py>=3.2.0
Requires-Dist: hdf5plugin>=4.1.3
Requires-Dist: ncempy<=1.11.2,>=1.8.1
Requires-Dist: matplotlib>=3.2.2
Requires-Dist: scikit-image>=0.17.2
Requires-Dist: scikit-learn<1.5,>=0.23.2
Requires-Dist: scikit-optimize>=0.9.0
Requires-Dist: tqdm>=4.46.1
Requires-Dist: dill>=0.3.3
Requires-Dist: gdown>=5.1.0
Requires-Dist: dask>=2.3.0
Requires-Dist: distributed>=2.3.0
Requires-Dist: emdfile>=0.0.14
Requires-Dist: mpire>=2.7.1
Requires-Dist: threadpoolctl>=3.1.0
Requires-Dist: pylops>=2.1.0
Requires-Dist: colorspacious>=1.1.2
Provides-Extra: ipyparallel
Requires-Dist: ipyparallel>=6.2.4; extra == "ipyparallel"
Requires-Dist: dill>=0.3.3; extra == "ipyparallel"
Provides-Extra: cuda
Requires-Dist: cupy>=10.0.0; extra == "cuda"
Provides-Extra: acom
Requires-Dist: pymatgen<2024.8.9,>=2022; extra == "acom"
Requires-Dist: mp-api==0.24.1; extra == "acom"
Provides-Extra: aiml
Requires-Dist: tensorflow<=2.10.0; extra == "aiml"
Requires-Dist: tensorflow-addons<=0.16.1; extra == "aiml"
Requires-Dist: crystal4D; extra == "aiml"
Requires-Dist: typeguard==2.7; extra == "aiml"
Provides-Extra: aiml-cuda
Requires-Dist: tensorflow<=2.10.0; extra == "aiml-cuda"
Requires-Dist: tensorflow-addons<=0.16.1; extra == "aiml-cuda"
Requires-Dist: crystal4D; extra == "aiml-cuda"
Requires-Dist: cupy>=10.0.0; extra == "aiml-cuda"
Requires-Dist: typeguard==2.7; extra == "aiml-cuda"
Provides-Extra: numba
Requires-Dist: numba>=0.49.1; extra == "numba"
Dynamic: author
Dynamic: author-email
Dynamic: description
Dynamic: description-content-type
Dynamic: home-page
Dynamic: keywords
Dynamic: license
Dynamic: provides-extra
Dynamic: requires-dist
Dynamic: requires-python
Dynamic: summary
